cheka/__init__.py
cheka/cheka.py
cheka/cli.py
cheka-0.7.dist-info/LICENSE
cheka-0.7.dist-info/METADATA
cheka-0.7.dist-info/WHEEL
cheka-0.7.dist-info/top_level.txt
cheka-0.7.dist-info/RECORD
