Metadata-Version: 2.1
Name: cheka
Version: 0.7
Summary: This tool validates a data graph against a set of SHACL shape graphs that it extracts from a hierarchy of Profiles (Standards/Specifications and/or profiles of them).
Home-page: https://github.com/surroundaustralia/cheka
Author: Nicholas Car
Author-email: nicholas.car@surroundaustralia.com
License: LICENSE
Download-URL: https://github.com/surroundaustralia/cheka/archive/0.7.tar.gz
Project-URL: Bug Reports, https://github.com/surroundaustralia/cheka/issues
Project-URL: Source, https://github.com/surroundaustralia/cheka/
Keywords: Semantic Web,OWL,ontology,SHACL,validation,profiles
Platform: UNKNOWN
Classifier: Development Status :: 4 - Beta
Classifier: Topic :: Utilities
Classifier: License :: OSI Approved :: GNU General Public License v3 or later (GPLv3+)
Classifier: Intended Audience :: Developers
Classifier: Natural Language :: English
Classifier: Programming Language :: Python :: 3
Classifier: Programming Language :: Python :: 3 :: Only
Classifier: Programming Language :: Python :: 3.5
Classifier: Programming Language :: Python :: 3.6
Classifier: Programming Language :: Python :: 3.7
Classifier: Programming Language :: Python :: Implementation :: CPython
Classifier: Programming Language :: Python :: Implementation :: PyPy
Classifier: Topic :: Software Development :: Libraries :: Python Modules
Requires-Dist: rdflib (>=6.0.0)
Requires-Dist: pyshacl
Requires-Dist: requests
Requires-Dist: pytest
